anti_sybil/__init__.py
anti_sybil/utils.py
anti_sybil/algorithms/__init__.py
anti_sybil/algorithms/group_sybil_rank.py
anti_sybil/algorithms/group_sybil_rank_v01.py
anti_sybil/algorithms/sybil_rank.py
anti_sybil/algorithms/weighted_sybil_rank.py
anti_sybil/templates/compare_graph.html
anti_sybil/templates/graph.html
anti_sybil-1.0.0.dist-info/LICENSE
anti_sybil-1.0.0.dist-info/METADATA
anti_sybil-1.0.0.dist-info/WHEEL
anti_sybil-1.0.0.dist-info/top_level.txt
anti_sybil-1.0.0.dist-info/RECORD
