Metadata-Version: 2.1
Name: anti-sybil
Version: 1.0.0
Summary: Anti sybil package for BrightID
Home-page: http://github.com/BrightID/BrightID-Node
Author: Abram Symons
Author-email: abram.symons@protonmail.com
License: UNKNOWN
Platform: UNKNOWN
Classifier: Programming Language :: Python :: 3.7
Classifier: License :: OSI Approved :: MIT License
Classifier: Operating System :: OS Independent
Requires-Dist: networkx (==2.1)
Requires-Dist: flask
Requires-Dist: requests
Requires-Dist: matplotlib
Requires-Dist: xmltodict
